asyncupbankapi/__init__.py
asyncupbankapi/client.py
asyncupbankapi/const.py
asyncupbankapi/exceptions.py
asyncupbankapi/httpSession.py
asyncupbankapi/models/__init__.py
asyncupbankapi/models/accounts.py
asyncupbankapi/models/baseModels.py
asyncupbankapi/models/categories.py
asyncupbankapi/models/tags.py
asyncupbankapi/models/transactions.py
asyncupbankapi/models/utility.py
asyncupbankapi/models/webhooks.py
upbankapi/__init__.py
upbankapi/client.py
upbankapi/const.py
upbankapi/exceptions.py
upbankapi/httpSession.py
async_up_bank_api-0.1.2.dist-info/LICENSE
async_up_bank_api-0.1.2.dist-info/METADATA
async_up_bank_api-0.1.2.dist-info/WHEEL
async_up_bank_api-0.1.2.dist-info/top_level.txt
async_up_bank_api-0.1.2.dist-info/RECORD
