Metadata-Version: 2.1
Name: async-up-bank-api
Version: 0.1.2
Summary: 💎 Typed python client for Up's banking API
Home-page: https://github.com/unchartedshark/async-up-bank-api
Author: Joshua Cowie-Willox & Jason Dau
Author-email: 
License: MIT
Download-URL: https://github.com/unchartedshark/async-up-bank-api/archive/v0.1.2.zip
Platform: any
Classifier: Programming Language :: Python :: 3.7
Classifier: Programming Language :: Python :: 3.8
Classifier: License :: OSI Approved :: MIT License
Classifier: Operating System :: OS Independent
Classifier: Development Status :: 3 - Alpha
Requires-Python: >=3.7
Requires-Dist: aiohttp (>=3.7.2)
Requires-Dist: pydantic (>=1.7.2)
